regression/PolynomialFunctions.py
regression/Regressors.py
regression/__init__.py
regression/utitilties.py
regression-1.0.5.dist-info/LICENSE
regression-1.0.5.dist-info/METADATA
regression-1.0.5.dist-info/WHEEL
regression-1.0.5.dist-info/top_level.txt
regression-1.0.5.dist-info/RECORD
