Metadata-Version: 2.1
Name: regression
Version: 1.0.5
Summary: Recreation of different kinds of regression using optimisation algorithms
Home-page: https://github.com/Muradmustafayev-03/RegressionRecreation.git
Author: Murad Mustafayev
Author-email: murad.mustafayev@ufaz.az
Project-URL: Bug Reports, https://github.com/Muradmustafayev-03/RegressionRecreation/issues
Project-URL: Funding, https://donate.pypi.org
Project-URL: Source, https://github.com/Muradmustafayev-03/RegressionRecreation/
Keywords: regression,linear regression,polynomial regression,multivariate regression,Artificial Intelligence,Machine Learning,Data Science,ML,AI
Classifier: Development Status :: 4 - Beta
Classifier: Intended Audience :: Science/Research
Classifier: Topic :: Scientific/Engineering :: Artificial Intelligence
Classifier: License :: OSI Approved :: GNU General Public License v3 (GPLv3)
Classifier: Programming Language :: Python :: 3
Classifier: Programming Language :: Python :: 3.7
Classifier: Programming Language :: Python :: 3.8
Classifier: Programming Language :: Python :: 3.9
Classifier: Programming Language :: Python :: 3.10
Classifier: Programming Language :: Python :: 3 :: Only
Requires-Python: >=3.7, <4
License-File: LICENSE
